mrtparse/__init__.py
mrtparse/base.py
mrtparse/params.py
mrtparse-2.1.0.dist-info/LICENSE
mrtparse-2.1.0.dist-info/METADATA
mrtparse-2.1.0.dist-info/WHEEL
mrtparse-2.1.0.dist-info/top_level.txt
mrtparse-2.1.0.dist-info/RECORD
