Metadata-Version: 2.1
Name: mrtparse
Version: 2.1.0
Summary: MRT format data parser
Home-page: https://github.com/t2mune/mrtparse
Author: Tetsumune KISO, Yoshiyuki YAMAUCHI, Nobuhiro ITOU
Author-email: t2mune@gmail.com, info@greenhippo.co.jp, js333123@gmail.com
License: Apache License 2.0
Keywords: mrt bgp
Platform: any
Classifier: Development Status :: 5 - Production/Stable
Classifier: Intended Audience :: Developers
Classifier: Intended Audience :: System Administrators
Classifier: Intended Audience :: Telecommunications Industry
Classifier: License :: OSI Approved :: Apache Software License
Classifier: Operating System :: OS Independent
Classifier: Programming Language :: Python :: 2
Classifier: Programming Language :: Python :: 3
Classifier: Programming Language :: Python :: Implementation :: PyPy
Classifier: Topic :: Internet
Classifier: Topic :: System :: Networking
License-File: LICENSE
